sbank-1.0.6.dist-info/COPYING
sbank-1.0.6.dist-info/RECORD
sbank-1.0.6.dist-info/METADATA
sbank-1.0.6.dist-info/WHEEL
sbank-1.0.6.dist-info/top_level.txt
sbank.libs/libfftw3f-4367ce36-f0b80d70.so.3.3.2
sbank.libs/libgslcblas-afe2feba-93152dca.so.0.0.0
sbank.libs/liblal-cc0817b5-c93a1a28.so.20.1.2
sbank.libs/libgsl-52a92e0b-6249efd0.so.25.1.0
sbank.libs/libfftw3-17cc48a2-30d466c9.so.3.3.2
sbank/overlap_cpu.cpython-36m-x86_64-linux-gnu.so
sbank/overlap.py
sbank/bank.py
sbank/psds.py
sbank/__init__.py
sbank/waveforms.py
sbank/tau0tau3.py
sbank/overlap_cuda.py
sbank/tests/__init__.py
sbank/tests/test_psds.py
sbank-1.0.6.data/scripts/sbank_choose_mchirp_boundaries
sbank-1.0.6.data/scripts/sbank_hdf5_choose_mchirp_boundaries
sbank-1.0.6.data/scripts/sbank_pipe
sbank-1.0.6.data/scripts/sbank_sim
sbank-1.0.6.data/scripts/sbank_sim_pipe
sbank-1.0.6.data/scripts/sbank_hdf5_bankcombiner
sbank-1.0.6.data/scripts/sbank
sbank-1.0.6.data/scripts/sbank_plot_sim
