Metadata-Version: 2.1
Name: sbank
Version: 1.0.6
Summary: A library for generating template banks of compact binary mergers for gravitational-wave searches using the "stochastic" placement algorithm
Home-page: https://github.com/gwastro/sbank
Author: The Sbank team
Maintainer: Ian Harry
Maintainer-email: ian.harry@ligo.org
License: GPL-2.0-or-later
Project-URL: Bug Tracker, https://github.com/gwastro/sbank/issues/
Project-URL: Source Code, https://github.com/gwastro/sbank
Platform: UNKNOWN
Classifier: Development Status :: 5 - Production/Stable
Classifier: Intended Audience :: Science/Research
Classifier: License :: OSI Approved :: GNU General Public License v2 or later (GPLv2+)
Classifier: Operating System :: MacOS
Classifier: Operating System :: POSIX
Classifier: Operating System :: Unix
Classifier: Programming Language :: Python :: 3
Classifier: Programming Language :: Python :: 3.6
Classifier: Programming Language :: Python :: 3.7
Classifier: Programming Language :: Python :: 3.8
Classifier: Programming Language :: Python :: 3.9
Classifier: Programming Language :: Python :: 3.10
Classifier: Programming Language :: Python :: 3.11
Classifier: Topic :: Scientific/Engineering :: Astronomy
Classifier: Topic :: Scientific/Engineering :: Physics
License-File: COPYING
Requires-Dist: h5py
Requires-Dist: lalsuite
Requires-Dist: lscsoft-glue
Requires-Dist: matplotlib
Requires-Dist: numpy
Requires-Dist: python-ligo-lw
Requires-Dist: scipy
Requires-Dist: six
